odoo/addons/web_send_message_popup/README.rst
odoo/addons/web_send_message_popup/__init__.py
odoo/addons/web_send_message_popup/__manifest__.py
odoo/addons/web_send_message_popup/i18n/web_send_message_popup.pot
odoo/addons/web_send_message_popup/readme/CONTRIBUTORS.rst
odoo/addons/web_send_message_popup/readme/DESCRIPTION.rst
odoo/addons/web_send_message_popup/static/description/icon.png
odoo/addons/web_send_message_popup/static/description/index.html
odoo/addons/web_send_message_popup/static/src/js/chatter.js
odoo/addons/web_send_message_popup/templates/assets.xml
odoo13_addon_web_send_message_popup-13.0.1.0.1.dev3.dist-info/METADATA
odoo13_addon_web_send_message_popup-13.0.1.0.1.dev3.dist-info/WHEEL
odoo13_addon_web_send_message_popup-13.0.1.0.1.dev3.dist-info/top_level.txt
odoo13_addon_web_send_message_popup-13.0.1.0.1.dev3.dist-info/RECORD
